__init__.py
picsign/__init__.py
picsign/command_line.py
picsign/pic_sign.py
picsign-0.0.11.dist-info/LICENSE
picsign-0.0.11.dist-info/METADATA
picsign-0.0.11.dist-info/WHEEL
picsign-0.0.11.dist-info/entry_points.txt
picsign-0.0.11.dist-info/top_level.txt
picsign-0.0.11.dist-info/RECORD
