Metadata-Version: 2.1
Name: picsign
Version: 0.0.11
Summary: a package to encrypt data in pictures
Author-email: Shobu Ser'Hao <lelu.awen@hacari.org>
License: GNU GENERAL PUBLIC LICENSE
Project-URL: Homepage, https://git.vraphim.com/shobu13/picsign
Project-URL: Bug Tracker, https://git.vraphim.com/shobu13/picsign
Classifier: Programming Language :: Python :: 3
Classifier: License :: OSI Approved :: GNU General Public License v3 (GPLv3)
Classifier: Operating System :: OS Independent
Requires-Python: >=3.7
License-File: LICENSE
Requires-Dist: Pillow
Requires-Dist: docopt
